vidshare/__init__.py
vidshare/streamer.py
vidshare-1.1.1.dist-info/METADATA
vidshare-1.1.1.dist-info/WHEEL
vidshare-1.1.1.dist-info/top_level.txt
vidshare-1.1.1.dist-info/RECORD
