Metadata-Version: 2.1
Name: vidshare
Version: 1.1.1
Summary: Streaming video and audio and screenshare data via networks
Home-page: UNKNOWN
Author: A.Jagan karthick
Author-email: <jagankarthick2@gmail.com>
License: UNKNOWN
Keywords: python,video,stream,video stream,camera stream,sockets
Platform: UNKNOWN
Classifier: Development Status :: 1 - Planning
Classifier: Intended Audience :: Developers
Classifier: Programming Language :: Python :: 3
Classifier: Operating System :: Unix
Classifier: Operating System :: MacOS :: MacOS X
Classifier: Operating System :: Microsoft :: Windows
Requires-Dist: opencv-python
Requires-Dist: Pillow
Requires-Dist: pyaudio
Requires-Dist: numpy
